pyrocon/__init__.py
pyrocon/conversation.py
pyrocon/errors.py
pyrocon-2.0.6.dist-info/METADATA
pyrocon-2.0.6.dist-info/WHEEL
pyrocon-2.0.6.dist-info/top_level.txt
pyrocon-2.0.6.dist-info/RECORD
