Metadata-Version: 2.1
Name: pyrocon
Version: 2.0.6
Summary: Easy conversation handler for pyrogram mtproto library...
Home-page: https://github.com/Surendra9123/Pyrocon
Author: SPiDER
Author-email: mindajitendra63@gmail.com
License: BSD
Keywords: example documentation tutorial
Classifier: Development Status :: 3 - Alpha
Classifier: Topic :: Utilities
Classifier: License :: OSI Approved :: BSD License
